COPYRIGHT
MANIFEST.in
setup.cfg
setup.py
bitmat/__init__.py
bitmat.egg-info/PKG-INFO
bitmat.egg-info/SOURCES.txt
bitmat.egg-info/dependency_links.txt
bitmat.egg-info/entry_points.txt
bitmat.egg-info/not-zip-safe
bitmat.egg-info/requires.txt
bitmat.egg-info/top_level.txt
tests/__init__.py
tests/data.py
tests/dbpedia.py
tests/test_fold.py
tests/test_join.py
tests/utils.py