Metadata-Version: 1.0
Name: bitmat
Version: 0.1.1dev
Summary: BitMat Index for RDFLib
Home-page: UNKNOWN
Author: William Waites
Author-email: wwaites_at_gmail.com
License: BSD
Keywords: rdf bitmat triplestore index
Platform: UNKNOWN
